vettavista_backend/__init__.py
vettavista_backend/config/__init__.py
vettavista_backend/config/global_constants.py
vettavista_backend/config/models.py
vettavista_backend/config/templates/ai_prompts.yaml
vettavista_backend/config/templates/ai_settings.yaml
vettavista_backend/config/templates/personals.yaml
vettavista_backend/config/templates/resume.yaml
vettavista_backend/config/templates/search.yaml
vettavista_backend/config/templates/secrets.yaml
vettavista_backend/modules/__init__.py
vettavista_backend/modules/server.py
vettavista_backend/modules/utils.py
vettavista_backend/modules/ai/__init__.py
vettavista_backend/modules/ai/claude_connections.py
vettavista_backend/modules/ai/prompts.py
vettavista_backend/modules/ai/protocols.py
vettavista_backend/modules/api/middleware.py
vettavista_backend/modules/api/utils.py
vettavista_backend/modules/api/rest/__init__.py
vettavista_backend/modules/api/rest/application_endpoints.py
vettavista_backend/modules/api/rest/base.py
vettavista_backend/modules/api/rest/blacklist_endpoints.py
vettavista_backend/modules/api/rest/filter_endpoints.py
vettavista_backend/modules/api/rest/job_history_endpoints.py
vettavista_backend/modules/api/websocket/__init__.py
vettavista_backend/modules/api/websocket/base.py
vettavista_backend/modules/api/websocket/editor_endpoints.py
vettavista_backend/modules/api/websocket/router.py
vettavista_backend/modules/api/websocket/sync_endpoints.py
vettavista_backend/modules/business/__init__.py
vettavista_backend/modules/business/application/application_service.py
vettavista_backend/modules/business/cache/job_cache_service.py
vettavista_backend/modules/business/filter/__init__.py
vettavista_backend/modules/business/filter/base.py
vettavista_backend/modules/business/filter/base_filter_service.py
vettavista_backend/modules/business/filter/detailed_filter_service.py
vettavista_backend/modules/business/filter/preliminary_filter_service.py
vettavista_backend/modules/business/utils/__init__.py
vettavista_backend-0.0.4.dist-info/METADATA
vettavista_backend-0.0.4.dist-info/WHEEL
vettavista_backend-0.0.4.dist-info/entry_points.txt
vettavista_backend-0.0.4.dist-info/RECORD
